voidscript/__init__.py
voidscript/utils.py
voidscript_python_wrapper-0.0.2.dist-info/METADATA
voidscript_python_wrapper-0.0.2.dist-info/WHEEL
voidscript_python_wrapper-0.0.2.dist-info/top_level.txt
voidscript_python_wrapper-0.0.2.dist-info/RECORD
