Metadata-Version: 2.1
Name: voidscript-python-wrapper
Version: 0.0.2
Summary: Wrapper for the VoidScript API
Home-page: https://github.com/rmountjoy92/VoidScriptPythonWrapper
Author: rmountjoy
Author-email: ross.mountjoy@gmail.com
License: UNKNOWN
Platform: UNKNOWN
Classifier: Programming Language :: Python :: 3
Classifier: License :: OSI Approved :: MIT License
Classifier: Operating System :: OS Independent
Requires-Python: >=3.6
Requires-Dist: requests (>=2)
Requires-Dist: six (>=1.10)
